nonebot_plugin_hammer_nbnhhsh/__init__.py
nonebot_plugin_hammer_nbnhhsh/config.py
nonebot_plugin_hammer_nbnhhsh/const.py
nonebot_plugin_hammer_nbnhhsh/handler.py
nonebot_plugin_hammer_nbnhhsh-1.0.0.dist-info/LICENSE
nonebot_plugin_hammer_nbnhhsh-1.0.0.dist-info/WHEEL
nonebot_plugin_hammer_nbnhhsh-1.0.0.dist-info/METADATA
nonebot_plugin_hammer_nbnhhsh-1.0.0.dist-info/RECORD
