Metadata-Version: 2.1
Name: nonebot-plugin-hammer-nbnhhsh
Version: 1.0.0
Summary: a nonebot2 plugin to request "nbnhhsh" api for qq group
Home-page: https://docs.hammer-hfut.tk:233
License: Apache-2.0
Author: ArgonarioD
Author-email: 739062975@qq.com
Requires-Python: >=3.9,<4.0
Classifier: License :: OSI Approved :: Apache Software License
Classifier: Programming Language :: Python :: 3
Classifier: Programming Language :: Python :: 3.10
Classifier: Programming Language :: Python :: 3.9
Requires-Dist: httpx (>=0.23.0,<0.24.0)
Requires-Dist: nonebot-plugin-hammer-core (>=0.1.1,<0.2.0)
Project-URL: Repository, https://github.com/ArgonarioD/nonebot-plugin-hammer-nbnhhsh
